glass_script/__init__.py
glass_script/main.py
glass_script-0.9.6.dist-info/LICENSE
glass_script-0.9.6.dist-info/METADATA
glass_script-0.9.6.dist-info/WHEEL
glass_script-0.9.6.dist-info/RECORD
