Metadata-Version: 2.3
Name: glass-script
Version: 0.9.6
Summary: GlassScript is a structured markup language.
License: MIT
Keywords: markup,html,accessibility,structured,language,easy
Author: splot.dev
Requires-Python: >=3.8
Classifier: License :: OSI Approved :: MIT License
Classifier: Programming Language :: Python :: 3
Classifier: Programming Language :: Python :: 3.8
Classifier: Programming Language :: Python :: 3.9
Classifier: Programming Language :: Python :: 3.10
Classifier: Programming Language :: Python :: 3.11
Classifier: Programming Language :: Python :: 3.12
Classifier: Programming Language :: Python :: 3.13
Requires-Dist: beautifulsoup4 (>=4.14.2,<5.0.0)
